Metadata-Version: 1.1
Name: storyblok-richtext
Version: 0.2.0
Summary: Storyblok Python library for Richtext component
Home-page: https://github.com/storyblok/storyblok-python-richtext-renderer
Author: Emanuel Souza
Author-email: eg@storyblok.com
License: MIT
Download-URL: https://github.com/storyblok/storyblok-python-richtext-renderer/archive/0.2.0.tar.gz
Platform: UNKNOWN
Classifier: Development Status :: 5 - Production/Stable
Classifier: Intended Audience :: Developers
Classifier: License :: OSI Approved :: MIT License
Classifier: Operating System :: OS Independent
Classifier: Programming Language :: Python :: 3.5
Classifier: Programming Language :: Python :: 3.7
Classifier: Topic :: Software Development :: Libraries :: Python Modules
